<?xml version="1.0" encoding="UTF-8"?>
<!--
 Licensed to the Apache Software Foundation (ASF) under one
 or more contributor license agreements.  See the NOTICE file
 distributed with this work for additional information
 regarding copyright ownership.  The ASF licenses this file
 to you under the Apache License, Version 2.0 (the
 "License"); you may not use this file except in compliance
 with the License.  You may obtain a copy of the License at

     http://www.apache.org/licenses/LICENSE-2.0

 Unless required by applicable law or agreed to in writing, software
 distributed under the License is distributed on an "AS IS" BASIS,
 WITHOUT WARRANTIES OR CONDITIONS OF ANY KIND, either express or implied.
 See the License for the specific language governing permissions and
 limitations under the License.
-->
<configuration>
  <property>
    <!--https://hadoop.apache.org/docs/stable/hadoop-project-dist/hadoop-hdfs/HdfsBlockPlacementPolicies.html-->
    <name>dfs.block.replicator.classname</name>
    <value>org.apache.hadoop.hdfs.server.blockmanagement.BlockPlacementPolicyRackFaultTolerant</value>
  </property>
  <property>
    <name>dfs.blocksize</name>
    <value>64m</value>
  </property>
  <property>
    <name>dfs.datanode.address</name>
    <value>0.0.0.0:9866</value>
  </property>
  <property>
    <name>dfs.datanode.balance.bandwidthPerSec</name>
    <value>20m</value>
  </property>
  <property>
    <name>dfs.datanode.balance.max.concurrent.moves</name>
    <value>100</value>
  </property>
  <property>
    <name>dfs.datanode.data.dir</name>
    <value>${env.DATANODE_DATA_DIR}</value>
  </property>
  <property>
    <name>dfs.datanode.failed.volumes.tolerated</name>
    <value>0</value>
  </property>
  <property>
    <name>dfs.datanode.du.reserved</name>
    <value>1073741824</value>
  </property>
  <property>
    <name>dfs.datanode.fileio.profiling.sampling.percentage</name>
    <value>10</value>
  </property>
  <property>
    <name>dfs.datanode.http.address</name>
    <value>0.0.0.0:9864</value>
  </property>
  <property>
    <name>dfs.datanode.https.address</name>
    <value>0.0.0.0:9865</value>
  </property>
  <property>
    <name>dfs.datanode.ipc.address</name>
    <value>0.0.0.0:9867</value>
  </property>
  <property>
    <name>dfs.datanode.max.locked.memory</name>
    <value>0</value>
  </property>
  <property>
    <name>dfs.datanode.peer.stats.enabled</name>
    <value>true</value>
  </property>
  <property>
    <name>dfs.encrypt.data.transfer</name>
    <value>false</value>
  </property>
  <property>
    <name>dfs.encrypt.data.transfer.algorithm</name>
    <value>rc4</value>
  </property>
  <property>
    <name>dfs.ha.automatic-failover.enabled</name>
    <value>true</value>
  </property>
  <property>
    <name>dfs.ha.fencing.methods</name>
    <value>shell(/usr/bin/true)</value>
  </property>
  <property>
    <name>dfs.journalnode.edits.dir</name>
    <value>${env.JOURNALNODE_DATA_DIR}</value>
  </property>
  <property>
    <name>dfs.journalnode.http-address</name>
    <value>0.0.0.0:8480</value>
  </property>
  <property>
    <name>dfs.journalnode.https-address</name>
    <value>0.0.0.0:8481</value>
  </property>
  <property>
    <name>dfs.journalnode.rpc-address</name>
    <value>0.0.0.0:8485</value>
  </property>
  <property>
    <name>dfs.namenode.handler.count</name>
    <value>64</value>
  </property>
  <!--
  <property>
    <name>dfs.hosts</name>
    <value>/tmp/scratch/hosts.json</value>
  </property>
  <property>
    <name>dfs.namenode.hosts.provider.classname</name>
    <value>org.apache.hadoop.hdfs.server.blockmanagement.CombinedHostFileManager</value>
  </property>
  -->
  <property>
    <name>dfs.namenode.http-bind-host</name>
    <value>0.0.0.0</value>
  </property>
  <property>
    <name>dfs.namenode.https-bind-host</name>
    <value>0.0.0.0</value>
  </property>
  <property>
    <name>dfs.namenode.name.dir</name>
    <value>${env.NAMENODE_DATA_DIR}</value>
  </property>
  <property>
    <name>dfs.namenode.replication.max-streams</name>
    <value>20</value>
  </property>
  <property>
    <name>dfs.namenode.replication.max-streams-hard-limit</name>
    <value>40</value>
  </property>
  <property>
    <name>dfs.namenode.replication.min</name>
    <value>3</value>
  </property>
  <property>
    <name>dfs.namenode.replication.work.multiplier.per.iteration</name>
    <value>10</value>
  </property>
  <property>
    <name>dfs.namenode.safemode.threshold-pct</name>
    <value>0.9</value>
  </property>
  <property>
    <name>dfs.namenode.service.handler.count</name>
    <value>64</value>
  </property>
  <property>
    <name>dfs.reformat.disabled</name>
    <value>false</value>
  </property>
  <property>
    <name>dfs.replication</name>
    <value>3</value>
  </property>
  <property>
    <name>dfs.replication.max</name>
    <value>512</value>
  </property>
  <property>
    <name>ipc.8020.callqueue.impl</name>
    <value>org.apache.hadoop.ipc.FairCallQueue</value>
  </property>
  <property>
    <name>ipc.8020.scheduler.impl</name>
    <value>org.apache.hadoop.ipc.DecayRpcScheduler</value>
  </property>
  <property>
    <name>zk-dt-secret-manager.zkAuthType</name>
    <value>digest</value>
  </property>
  <property>
    <name>zk-dt-secret-manager.digest.auth</name>
    <value>@/etc/hadoop/zookeeper/auth/zk-auth.txt</value>
  </property>
  <property>
    <name>zk-dt-secret-manager.zkConnectionString</name>
    <value>TODO</value>
  </property>
  <property>
    <name>zk-dt-secret-manager.znodeWorkingPath</name>
    <value>TODO</value>
  </property>
  <property>
    <name>dfs.client.failover.proxy.provider.hadoop</name>
    <value>org.apache.hadoop.hdfs.server.namenode.ha.ConfiguredFailoverProxyProvider</value>
  </property>

  <property>
    <name>dfs.client.https.keystore.resource</name>
    <value>ssl-client.xml</value>
  </property>
  <property>
    <name>dfs.client.https.need-auth</name>
    <value>false</value>
  </property>
  <property>
    <name>dfs.http.policy</name>
    <value>${env.HTTP_POLICY}</value>
  </property>
  <property>
    <name>dfs.https.enable</name>
    <value>${env.DFS_HTTPS_ENABLE}</value>
  </property>
  <property>
    <name>dfs.https.server.keystore.resource</name>
    <value>ssl-server.xml</value>
  </property>
  <property>
    <name>dfs.namenode.acls.enabled</name>
    <value>true</value>
  </property>
  <property>
    <!--From https://hadoop.apache.org/docs/stable/hadoop-project-dist/hadoop-hdfs/HdfsMultihoming.html -->
    <name>dfs.datanode.use.datanode.hostname</name>
    <value>true</value>
  </property>
  <property>
    <!--https://log.rowanto.com/posts/why-datanode-is-denied-communication-with-namenode/-->
    <name>dfs.namenode.datanode.registration.ip-hostname-check</name>
    <value>false</value>
  </property>
  <property>
    <name>dfs.namenode.shared.edits.dir</name>
    <value>${env.QJOURNAL}</value>
  </property>
  <property>
    <name>dfs.nameservices</name>
    <value>${env.HADOOP_SERVICE}</value>
  </property>
  <property>
    <name>dfs.ha.namenodes.hadoop</name>
    <value>namenode-0,namenode-1,namenode-2</value>
  </property>
  <property>
    <name>dfs.namenode.http-address.hadoop.namenode-0</name>
    <value>namenode-0.${env.HADOOP_SERVICE}.${env.POD_NAMESPACE}.${env.DOMAIN}:9870</value>
  </property>
  <property>
    <name>dfs.namenode.https-address.hadoop.namenode-0</name>
    <value>namenode-0.${env.HADOOP_SERVICE}.${env.POD_NAMESPACE}.${env.DOMAIN}:9871</value>
  </property>
  <property>
    <name>dfs.namenode.rpc-address.hadoop.namenode-0</name>
    <value>namenode-0.${env.HADOOP_SERVICE}.${env.POD_NAMESPACE}.${env.DOMAIN}:8020</value>
    <description>RPC address that handles all clients requests. In the case of
      HA/Federation where multiple namenodes exist, the name service id is added
      to the name e.g. dfs.namenode.rpc-address.ns1 dfs.namenode.rpc-address.EXAMPLENAMESERVICE
      The value of this property will take the form of nn-host1:rpc-port.

      Uses the value here to find its local name. The value here must be useable
      making a resolvable inetsocketaddress and then pass the is local test.
    </description>
  </property>
  <property>
    <name>dfs.namenode.servicerpc-address.hadoop.namenode-0</name>
    <!--Service name-->
    <value>namenode-0.${env.HADOOP_SERVICE}.${env.POD_NAMESPACE}.${env.DOMAIN}:8022</value>
  </property>
  <property>
    <name>dfs.namenode.lifeline.rpc-address.hadoop.namenode-0</name>
    <value>namenode-0.${env.HADOOP_SERVICE}.${env.POD_NAMESPACE}.${env.DOMAIN}:8050</value>
  </property>
  <property>
    <name>dfs.namenode.http-address.hadoop.namenode-1</name>
    <value>namenode-1.${env.HADOOP_SERVICE}.${env.POD_NAMESPACE}.${env.DOMAIN}:9870</value>
  </property>
  <property>
    <name>dfs.namenode.https-address.hadoop.namenode-1</name>
    <value>namenode-1.${env.HADOOP_SERVICE}.${env.POD_NAMESPACE}.${env.DOMAIN}:9871</value>
  </property>
  <property>
    <name>dfs.namenode.rpc-address.hadoop.namenode-1</name>
    <value>namenode-1.${env.HADOOP_SERVICE}.${env.POD_NAMESPACE}.${env.DOMAIN}:8020</value>
  </property>
  <property>
    <name>dfs.namenode.servicerpc-address.hadoop.namenode-1</name>
    <!--Service name-->
    <value>namenode-1.${env.HADOOP_SERVICE}.${env.POD_NAMESPACE}.${env.DOMAIN}:8022</value>
  </property>
  <property>
    <name>dfs.namenode.lifeline.rpc-address.hadoop.namenode-1</name>
    <value>namenode-1.${env.HADOOP_SERVICE}.${env.POD_NAMESPACE}.${env.DOMAIN}:8050</value>
  </property>
  <property>
    <name>dfs.namenode.http-address.hadoop.namenode-2</name>
    <value>namenode-2.${env.HADOOP_SERVICE}.${env.POD_NAMESPACE}.${env.DOMAIN}:9870</value>
  </property>
  <property>
    <name>dfs.namenode.https-address.${HADOOP_SERVICE}.namenode-2</name>
    <value>namenode-2.${env.HADOOP_SERVICE}.${env.POD_NAMESPACE}.${env.DOMAIN}:9871</value>
  </property>
  <property>
    <name>dfs.namenode.rpc-address.hadoop.namenode-2</name>
    <value>namenode-2.${env.HADOOP_SERVICE}.${env.POD_NAMESPACE}.${env.DOMAIN}:8020</value>
  </property>
  <property>
    <name>dfs.namenode.servicerpc-address.hadoop.namenode-2</name>
    <!--Service nme-->
    <value>namenode-2.${env.HADOOP_SERVICE}.${env.POD_NAMESPACE}.${env.DOMAIN}:8022</value>
  </property>
  <property>
    <name>dfs.namenode.lifeline.rpc-address.hadoop.namenode-2</name>
    <value>namenode-2.${env.HADOOP_SERVICE}.${env.POD_NAMESPACE}.${env.DOMAIN}:8050</value>
  </property>
  <property>
    <name>dfs.blockreport.intervalMsec</name>
    <value>900000</value>
    <description>Determines block reporting interval in milliseconds.
    Report frequently else around recovery storms, the NN gets convinced
    there is no block space left because of 'scheduled space' reserved.
    </description>
  </property>
</configuration>
